cally/cdk/__init__.py
cally/cdk/py.typed
cally/cdk/resources/__init__.py
cally/cdk/stacks/__init__.py
cally/cli/__init__.py
cally/cli/_version.py
cally/cli/constants.py
cally/cli/exceptions.py
cally/cli/py.typed
cally/cli/commands/__init__.py
cally/cli/commands/config.py
cally/cli/commands/provider.py
cally/cli/commands/tf.py
cally/cli/config/__init__.py
cally/cli/config/config_types.py
cally/cli/config/environment.py
cally/cli/config/mixins.py
cally/cli/config/options.py
cally/cli/config/service.py
cally/cli/config/terraform_service.py
cally/cli/config/validators.py
cally/cli/config/loaders/__init__.py
cally/cli/config/loaders/environment.py
cally/cli/config/loaders/service.py
cally/cli/tools/__init__.py
cally/cli/tools/provider.py
cally/cli/tools/terraform.py
cally/testing/__init__.py
cally/testing/constants.py
cally/testing/exceptions.py
cally/testing/py.typed
cally-0.6.0.dist-info/LICENSE
cally-0.6.0.dist-info/METADATA
cally-0.6.0.dist-info/WHEEL
cally-0.6.0.dist-info/entry_points.txt
cally-0.6.0.dist-info/top_level.txt
cally-0.6.0.dist-info/RECORD
