Metadata-Version: 2.1
Name: cally
Version: 0.6.0
Summary: A config as infrastructure foundation for your Internal Developer Platform
Author-email: Leon Wright <techman83@gmail.com>
License: Mozilla Public License Version 2.0
Project-URL: Repository, https://github.com/CallyCo-io/Cally/
Project-URL: Issues, https://github.com/CallyCo-io/Cally/issues
Requires-Python: >=3.8
License-File: LICENSE
Requires-Dist: cdktf
Requires-Dist: click
Requires-Dist: dynaconf
Requires-Dist: PyYAML
Provides-Extra: development
Requires-Dist: black; extra == "development"
Requires-Dist: build; extra == "development"
Requires-Dist: isort; extra == "development"
Requires-Dist: mypy; extra == "development"
Requires-Dist: coverage; extra == "development"
Requires-Dist: pytest; extra == "development"
Requires-Dist: pytest-black; extra == "development"
Requires-Dist: pytest-mypy; extra == "development"
Requires-Dist: pytest-ruff; extra == "development"
Requires-Dist: ruff; extra == "development"
Requires-Dist: types-PyYAML; extra == "development"
Requires-Dist: sphinx; extra == "development"
Requires-Dist: sphinx-autobuild; extra == "development"
Requires-Dist: sphinx-issues; extra == "development"
Requires-Dist: sphinxcontrib-log-cabinet; extra == "development"
Requires-Dist: sphinx-tabs; extra == "development"
Requires-Dist: sphinx-click; extra == "development"
Requires-Dist: Pallets-Sphinx-Themes; extra == "development"
Provides-Extra: test
Requires-Dist: black; extra == "test"
Requires-Dist: build; extra == "test"
Requires-Dist: coverage; extra == "test"
Requires-Dist: mypy; extra == "test"
Requires-Dist: pytest; extra == "test"
Requires-Dist: pytest-black; extra == "test"
Requires-Dist: pytest-mypy; extra == "test"
Requires-Dist: pytest-ruff; extra == "test"
Requires-Dist: ruff; extra == "test"
Requires-Dist: types-PyYAML; extra == "test"
Provides-Extra: provider-build
Requires-Dist: build; extra == "provider-build"
Provides-Extra: docs
Requires-Dist: sphinx; extra == "docs"
Requires-Dist: sphinx-issues; extra == "docs"
Requires-Dist: sphinxcontrib-log-cabinet; extra == "docs"
Requires-Dist: sphinx-tabs; extra == "docs"
Requires-Dist: sphinx-click; extra == "docs"
Requires-Dist: Pallets-Sphinx-Themes; extra == "docs"
